oca_odoo_pre_commit_hooks-0.2.20.data/data/requirements/requirements.txt
oca_odoo_pre_commit_hooks-0.2.20.dist-info/licenses/LICENSE
oca_pre_commit_hooks/__init__.py
oca_pre_commit_hooks/__main__.py
oca_pre_commit_hooks/base_checker.py
oca_pre_commit_hooks/checks_odoo_module.py
oca_pre_commit_hooks/checks_odoo_module_csv.py
oca_pre_commit_hooks/checks_odoo_module_fixit.py
oca_pre_commit_hooks/checks_odoo_module_fixit_common.py
oca_pre_commit_hooks/checks_odoo_module_po.py
oca_pre_commit_hooks/checks_odoo_module_xml.py
oca_pre_commit_hooks/cli.py
oca_pre_commit_hooks/cli_fixit.py
oca_pre_commit_hooks/cli_po.py
oca_pre_commit_hooks/global_parser.py
oca_pre_commit_hooks/node_xml.py
oca_pre_commit_hooks/utils.py
oca_pre_commit_hooks/checks_odoo_module_fixit_rules/__init__.py
oca_pre_commit_hooks/checks_odoo_module_fixit_rules/field_string_redundant.py
oca_pre_commit_hooks/checks_odoo_module_fixit_rules/manifest_superfluous_key_rule.py
oca_pre_commit_hooks/checks_odoo_module_fixit_rules/prefer_env_translation.py
oca_pre_commit_hooks/checks_odoo_module_fixit_rules/unused_logger.py
oca_odoo_pre_commit_hooks-0.2.20.dist-info/METADATA
oca_odoo_pre_commit_hooks-0.2.20.dist-info/WHEEL
oca_odoo_pre_commit_hooks-0.2.20.dist-info/entry_points.txt
oca_odoo_pre_commit_hooks-0.2.20.dist-info/top_level.txt
oca_odoo_pre_commit_hooks-0.2.20.dist-info/RECORD
