Metadata-Version: 2.4
Name: oca-odoo-pre-commit-hooks
Version: 0.2.20
Summary: odoo-pre-commit-hooks to use in pre-commit-config.yml files
Home-page: https://github.com/OCA/odoo-pre-commit-hooks
Author: Odoo Community Association (OCA)
Author-email: support@odoo-community.org
License: LGPL-3.0-or-later
Project-URL: Issue Tracker, https://github.com/OCA/odoo-pre-commit-hooks/issues
Keywords: pre-commit,OCA,Odoo Community Association,pre-commit-hook
Classifier: Development Status :: 5 - Production/Stable
Classifier: Intended Audience :: Developers
Classifier: License :: OSI Approved :: GNU Lesser General Public License v3 or later (LGPLv3+)
Classifier: Operating System :: Unix
Classifier: Operating System :: POSIX
Classifier: Operating System :: Microsoft :: Windows
Classifier: Operating System :: MacOS
Classifier: Programming Language :: Python :: 3
Classifier: Programming Language :: Python :: 3.10
Classifier: Programming Language :: Python :: 3.11
Classifier: Programming Language :: Python :: 3.12
Classifier: Programming Language :: Python :: 3.13
Classifier: Programming Language :: Python :: 3.14
Classifier: Topic :: Utilities
Requires-Python: >=3.9
License-File: LICENSE
Requires-Dist: colorama
Requires-Dist: fixit==2.2.1
Requires-Dist: lxml>=4.2.3
Requires-Dist: packaging
Requires-Dist: polib==1.2.*
Dynamic: author
Dynamic: author-email
Dynamic: classifier
Dynamic: description
Dynamic: description-content-type
Dynamic: home-page
Dynamic: keywords
Dynamic: license
Dynamic: license-file
Dynamic: project-url
Dynamic: requires-dist
Dynamic: requires-python
Dynamic: summary
